CHANGELOG.md
ya_django_toolkit_jp/__init__.py
ya_django_toolkit_jp/apps.py
ya_django_toolkit_jp/base/__init__.py
ya_django_toolkit_jp/base/models/__init__.py
ya_django_toolkit_jp/base/models/base.py
ya_django_toolkit_jp/base/models/base_ulid.py
ya_django_toolkit_jp/base/models/base_uuid.py
ya_django_toolkit_jp/base/models/ulid.py
ya_django_toolkit_jp/base_app_settings.py
ya_django_toolkit_jp/fields/__init__.py
ya_django_toolkit_jp/fields/normalize_char_field.py
ya_django_toolkit_jp/fields/ulid.py
ya_django_toolkit_jp/ja/__init__.py
ya_django_toolkit_jp/ja/fields/__init__.py
ya_django_toolkit_jp/ja/fields/hiragana_char.py
ya_django_toolkit_jp/ja/fields/katakana_char.py
ya_django_toolkit_jp/ja/utils.py
ya_django_toolkit_jp/ja/validators/__init__.py
ya_django_toolkit_jp/ja/validators/hiragana_only.py
ya_django_toolkit_jp/ja/validators/katakana_only.py
ya_django_toolkit_jp/templatetags/__init__.py
ya_django_toolkit_jp/templatetags/ya_django_toolkit_jp.py
ya_django_toolkit_jp/utils/__init__.py
ya_django_toolkit_jp/utils/file.py
ya_django_toolkit_jp/utils/ip.py
ya_django_toolkit_jp/utils/ipv6.py
ya_django_toolkit_jp/utils/mimetypes.py
ya_django_toolkit_jp/utils/view.py
ya_django_toolkit_jp-0.0.3.dist-info/METADATA
ya_django_toolkit_jp-0.0.3.dist-info/WHEEL
ya_django_toolkit_jp-0.0.3.dist-info/RECORD
